roro/__init__.py
roro/auth.py
roro/cli.py
roro/client.py
roro/config.py
roro/helpers.py
roro/models.py
roro/path.py
roro/projects.py
roro/serializers.py
roro-0.1.16.dist-info/DESCRIPTION.rst
roro-0.1.16.dist-info/METADATA
roro-0.1.16.dist-info/RECORD
roro-0.1.16.dist-info/WHEEL
roro-0.1.16.dist-info/entry_points.txt
roro-0.1.16.dist-info/metadata.json
roro-0.1.16.dist-info/top_level.txt
tests/__init__.py
tests/test_cli.py
tests/test_helpers.py
tests/test_projects.py
tests/test_serializers.py
